{"mapping": [{"column_header": "Seismic Waves", "dbpedia_property_id": "http://dbpedia.org/ontology/geology"}, {"column_header": "Reflection Coefficient", "dbpedia_property_id": "http://dbpedia.org/ontology/albedo"}, {"column_header": "Velocity Structure", "dbpedia_property_id": "http://dbpedia.org/ontology/geology"}, {"column_header": "Layer Thickness", "dbpedia_property_id": "http://dbpedia.org/ontology/depth"}, {"column_header": "Frequency Bands", "dbpedia_property_id": "http://dbpedia.org/ontology/band"}, {"column_header": "Amplitude", "dbpedia_property_id": "http://dbpedia.org/ontology/strength"}, {"column_header": "Phase", "dbpedia_property_id": "http://dbpedia.org/ontology/frequency"}, {"column_header": "Subsurface Imaging Techniques", "dbpedia_property_id": "http://dbpedia.org/ontology/technique"}, {"column_header": "Geologic Hazard Assessment", "dbpedia_property_id": "http://dbpedia.org/ontology/geologicPeriod"}, {"column_header": "Free Surface Effect", "dbpedia_property_id": "http://dbpedia.org/ontology/surfaceType"}, {"column_header": "Topographic Corrections", "dbpedia_property_id": "http://dbpedia.org/ontology/nationalTopographicSystemMapNumber"}, {"column_header": "Sea Level Changes", "dbpedia_property_id": "http://dbpedia.org/ontology/sea"}]}