{
  "mapping": [
    {"column_header": "Additional Data", "dbpedia_property_id": "http://dbpedia.org/ontology/otherInformation"},
    {"column_header": " Study Area ID", "dbpedia_property_id": "http://dbpedia.org/ontology/id"},
    {"column_header": " Date & Time Stamp", "dbpedia_property_id": "http://dbpedia.org/ontology/recordDate"},
    {"column_header": " Satellite Image Reference", "dbpedia_property_id": "http://dbpedia.org/ontology/satellite"},
    {"column_header": " Land Type Classification", "dbpedia_property_id": "http://dbpedia.org/ontology/classification"},
    {"column_header": " Snow Coverage (+/-)", "dbpedia_property_id": "http://dbpedia.org/ontology/percentage"},
    {"column_header": " Freeze Index Value", "dbpedia_property_id": "http://dbpedia.org/ontology/value"},
    {"column_header": " Evapotranspiration Rate (kg/(hm^2))", "dbpedia_property_id": "http://dbpedia.org/ontology/value"},
    {"column_header": " Heat Wave Duration (days)", "dbpedia_property_id": "http://dbpedia.org/ontology/value"},
    {"column_header": " Storm Cell Tracking Category (- none – assigned if exists–)", "dbpedia_property_id": "http://dbpedia.org/ontology/notes"},
    {"column_header": " Temperature (°F)", "dbpedia_property_id": "http://dbpedia.org/ontology/temperature"},
    {"column_header": " Relative Humidity (%)", "dbpedia_property_id": "http://dbpedia.org/ontology/percentage"},
    {"column_header": " Atmospheric Pressure (inHg)", "dbpedia_property_id": "http://dbpedia.org/ontology/vaporPressure"}
  ]
}