{"mapping":[{"column_header":"God","dbpedia_property_id":"http://dbpedia.org/ontology/enshrinedDeity"},{"column_header":"Spouse(ves)","dbpedia_property_id":"http://dbpedia.org/ontology/spouse"},{"column_header":"Children","dbpedia_property_id":"http://dbpedia.org/ontology/child"},{"column_header":"Divine Tools/Attributes","dbpedia_property_id":"http://dbpedia.org/ontology/iconographicAttributes"},{"column_header":"Domains","dbpedia_property_id":"http://dbpedia.org/ontology/domain"},{"column_header":"Mythmaking Role","dbpedia_property_id":"http://dbpedia.org/ontology/role"},{"column_header":"Godly Responsibilities & Powers","dbpedia_property_id":"http://dbpedia.org/ontology/power"},{"column_header":"#Zombies","dbpedia_property_id":"http://dbpedia.org/ontology/related"},{"column_header":"Taboo Actions","dbpedia_property_id":"http://dbpedia.org/ontology/discipline"},{"column_header":"Rituals/Sacrifices","dbpedia_property_id":"http://dbpedia.org/ontology/religion"},{"column_header":"Festivals / Holy Days","dbpedia_property_id":"http://dbpedia.org/ontology/feastDay"},{"column_header":"Moral Teachings","dbpedia_property_id":"http://dbpedia.org/ontology/ideology"},{"column_header":"*Animals Associations*","dbpedia_property_id":"http://dbpedia.org/ontology/fauna"}]}