{"mapping": [{"column_header": "Poet Biography", "dbpedia_property_id": "http://dbpedia.org/ontology/author"}, {"column_header": "Publications List", "dbpedia_property_id": "http://dbpedia.org/ontology/publication"}, {"column_header": "Poetry Language Origin", "dbpedia_property_id": "http://dbpedia.org/ontology/originalLanguage"}, {"column_header": "Cultural Context", "dbpedia_property_id": "http://dbpedia.org/ontology/refcul"}, {"column_header": "Inspiration Sources", "dbpedia_property_id": "http://dbpedia.org/ontology/source"}, {"column_header": "Formative Experiences", "dbpedia_property_id": "http://dbpedia.org/ontology/mentor"}, {"column_header": "Education Background & Mentors", "dbpedia_property_id": "http://dbpedia.org/ontology/education"}, {"column_header": "Style Evolution Over Time", "dbpedia_property_id": "http://dbpedia.org/ontology/style"}, {"column_header": "Prevalence Of Personal Themes", "dbpedia_property_id": "http://dbpedia.org/ontology/ethnicity"}, {"column_header": "Collaborators And Peers", "dbpedia_property_id": "http://dbpedia.org/ontology/collaboration"}]}