{"mapping": [{"column_header": "Additional Tests Recommended", "dbpedia_property_id": "http://dbpedia.org/ontology/medicalDiagnosis"}, {"column_header": "Medicine Prescribed", "dbpedia_property_id": "http://dbpedia.org/ontology/medication"}, {"column_header": "Dosage Instructions", "dbpedia_property_id": "http://dbpedia.org/ontology/dose"}, {"column_header": "Surgery Performed", "dbpedia_property_id": "http://dbpedia.org/ontology/treatment"}, {"column_header": "Surgeon Notes", "dbpedia_property_id": "http://dbpedia.org/ontology/notes"}, {"column_header": "Recovery Progress", "dbpedia_property_id": "http://dbpedia.org/ontology/recoveryCases"}, {"column_header": "Special Dietary Needs", "dbpedia_property_id": "http://dbpedia.org/ontology/requirement"}, {"column_header": "Exercise Requirements", "dbpedia_property_id": "http://dbpedia.org/ontology/activity"}, {"column_header": "Behavioral Modifications Suggested", "dbpedia_property_id": "http://dbpedia.org/ontology/requirement"}, {"column_header": "Referral to Specialist Details", "dbpedia_property_id": "http://dbpedia.org/ontology/specialist"}, {"column_header": "Appointment Schedule Reminders", "dbpedia_property_id": "http://dbpedia.org/ontology/eventDate"}, {"column_header": "Fees and Payments Due Dates", "dbpedia_property_id": "http://dbpedia.org/ontology/fees"}, {"column_header": "Owner Education Materials", "dbpedia_property_id": "http://dbpedia.org/ontology/education"}]}